{
  "accentColor": "{{appsmith.theme.colors.primaryColor}}",
  "animateLoading": true,
  "autoFocus": false,
  "borderRadius": "{{appsmith.theme.borderRadius.appBorderRadius}}",
  "bottomRow": 18,
  "boxShadow": "none",
  "defaultText": "{{Values.filterClientInfo(getOneClient.data.value[0]).codeclient}}",
  "displayName": "Input",
  "dynamicBindingPathList": [
    {
      "key": "accentColor"
    },
    {
      "key": "borderRadius"
    },
    {
      "key": "defaultText"
    }
  ],
  "dynamicHeight": "FIXED",
  "dynamicTriggerPathList": [],
  "hideCard": false,
  "iconAlign": "left",
  "iconSVG": "/static/media/icon.9f505595da61a34f563dba82adeb06ec.svg",
  "inputType": "TEXT",
  "isDeprecated": false,
  "isDisabled": true,
  "isLoading": false,
  "isRequired": false,
  "isVisible": true,
  "key": "fxo7oidhhd",
  "label": "Code Client",
  "labelAlignment": "left",
  "labelPosition": "Left",
  "labelStyle": "",
  "labelTextSize": "0.875rem",
  "labelWidth": "12",
  "leftColumn": 1,
  "maxDynamicHeight": 9000,
  "minDynamicHeight": 4,
  "parentColumnSpace": 7,
  "parentId": "jsaif5g0w9",
  "parentRowSpace": 10,
  "renderMode": "CANVAS",
  "resetOnSubmit": true,
  "rightColumn": 27,
  "searchTags": [
    "form",
    "text input",
    "number",
    "textarea"
  ],
  "topRow": 14,
  "type": "INPUT_WIDGET_V2",
  "version": 2,
  "widgetId": "cso9lf7tzo",
  "widgetName": "Input3Copy"
}