{
  "animateLoading": true,
  "borderRadius": "{{appsmith.theme.borderRadius.appBorderRadius}}",
  "bottomRow": 63,
  "boxShadow": "none",
  "buttonColor": "{{appsmith.theme.colors.primaryColor}}",
  "buttonStyle": "PRIMARY",
  "buttonVariant": "SECONDARY",
  "disabledWhenInvalid": false,
  "displayName": "Button",
  "dynamicBindingPathList": [
    {
      "key": "buttonColor"
    },
    {
      "key": "borderRadius"
    }
  ],
  "dynamicTriggerPathList": [],
  "hideCard": false,
  "iconSVG": "/static/media/icon.cca026338f1c8eb6df8ba03d084c2fca.svg",
  "isDefaultClickDisabled": true,
  "isDeprecated": false,
  "isDisabled": false,
  "isLoading": false,
  "isVisible": true,
  "key": "fpd50gbw4k",
  "leftColumn": 9,
  "onClick": "{{closeModal('AskModificationModal')}}",
  "parentId": "j9bk29jhl4",
  "placement": "CENTER",
  "recaptchaType": "V3",
  "renderMode": "CANVAS",
  "resetFormOnClick": false,
  "rightColumn": 25,
  "searchTags": [
    "click",
    "submit"
  ],
  "text": "Annuler",
  "topRow": 59,
  "type": "BUTTON_WIDGET",
  "version": 1,
  "widgetId": "k52w77yedc",
  "widgetName": "Button2"
}